{
  "annotations": {
    "list": []
  },
  "description": "MetaLayer Airflow & Data Pipeline Dashboard - Fixed",
  "editable": true,
  "fiscalYearStartMonth": 0,
  "graphTooltip": 0,
  "id": null,
  "links": [],
  "liveNow": false,
  "panels": [
    {
      "datasource": {
        "type": "postgres",
        "uid": "postgres"
      },
      "fieldConfig": {
        "defaults": {
          "color": {
            "mode": "palette-classic"
          },
          "custom": {
            "hideFrom": {
              "legend": false,
              "tooltip": false,
              "vis": false
            }
          },
          "mappings": []
        }
      },
      "gridPos": {
        "h": 8,
        "w": 12,
        "x": 0,
        "y": 0
      },
      "id": 1,
      "options": {
        "legend": {
          "displayMode": "table",
          "placement": "right",
          "showLegend": true,
          "values": ["value"]
        },
        "pieType": "pie",
        "reduceOptions": {
          "values": false,
          "calcs": ["lastNotNull"],
          "fields": ""
        }
      },
      "targets": [
        {
          "datasource": {
            "type": "postgres",
            "uid": "postgres"
          },
          "format": "table",
          "rawQuery": true,
          "rawSql": "SELECT schemaname as layer, count(*) as tables FROM pg_tables WHERE schemaname IN ('bronze', 'silver', 'gold') GROUP BY schemaname ORDER BY schemaname;",
          "refId": "A"
        }
      ],
      "title": "Layer Record Counts",
      "type": "piechart"
    },
    {
      "datasource": {
        "type": "postgres",
        "uid": "postgres"
      },
      "fieldConfig": {
        "defaults": {
          "color": {
            "mode": "thresholds"
          },
          "custom": {
            "align": "auto",
            "displayMode": "auto",
            "inspect": false
          },
          "mappings": [],
          "thresholds": {
            "mode": "absolute",
            "steps": [
              {
                "color": "green",
                "value": null
              }
            ]
          }
        }
      },
      "gridPos": {
        "h": 8,
        "w": 12,
        "x": 12,
        "y": 0
      },
      "id": 2,
      "options": {
        "showHeader": true
      },
      "targets": [
        {
          "datasource": {
            "type": "postgres",
            "uid": "postgres"
          },
          "format": "table",
          "rawQuery": true,
          "rawSql": "SELECT schemaname as schema, count(*) as table_count FROM pg_tables WHERE schemaname IN ('bronze', 'silver', 'gold') GROUP BY schemaname ORDER BY schemaname;",
          "refId": "A"
        }
      ],
      "title": "Database Schemas Overview",
      "type": "table"
    },
    {
      "datasource": {
        "type": "postgres",
        "uid": "postgres"
      },
      "fieldConfig": {
        "defaults": {
          "color": {
            "mode": "thresholds"
          },
          "custom": {
            "align": "auto",
            "displayMode": "auto",
            "inspect": false
          },
          "mappings": [],
          "thresholds": {
            "mode": "absolute",
            "steps": [
              {
                "color": "green",
                "value": null
              }
            ]
          }
        }
      },
      "gridPos": {
        "h": 8,
        "w": 24,
        "x": 0,
        "y": 8
      },
      "id": 3,
      "options": {
        "showHeader": true
      },
      "targets": [
        {
          "datasource": {
            "type": "postgres",
            "uid": "postgres"
          },
          "format": "table",
          "rawQuery": true,
          "rawSql": "SELECT dag_id, state, count(*) as runs, max(execution_date) as last_execution FROM dag_run WHERE execution_date >= current_date - interval '7 days' GROUP BY dag_id, state ORDER BY last_execution DESC LIMIT 20;",
          "refId": "A"
        }
      ],
      "title": "Recent DAG Runs (7 days)",
      "type": "table"
    },
    {
      "datasource": {
        "type": "postgres",
        "uid": "postgres"
      },
      "fieldConfig": {
        "defaults": {
          "color": {
            "mode": "thresholds"
          },
          "custom": {
            "align": "auto",
            "displayMode": "auto",
            "inspect": false
          },
          "mappings": [],
          "thresholds": {
            "mode": "absolute",
            "steps": [
              {
                "color": "green",
                "value": null
              }
            ]
          }
        }
      },
      "gridPos": {
        "h": 8,
        "w": 24,
        "x": 0,
        "y": 16
      },
      "id": 4,
      "options": {
        "showHeader": true
      },
      "targets": [
        {
          "datasource": {
            "type": "postgres",
            "uid": "postgres"
          },
          "format": "table",
          "rawQuery": true,
          "rawSql": "SELECT t.schemaname as schema, t.tablename as table_name, pg_size_pretty(pg_total_relation_size(c.oid)) as size FROM pg_tables t JOIN pg_class c ON c.relname = t.tablename JOIN pg_namespace n ON n.oid = c.relnamespace AND n.nspname = t.schemaname WHERE t.schemaname IN ('bronze', 'silver', 'gold') ORDER BY t.schemaname, t.tablename;",
          "refId": "A"
        }
      ],
      "title": "Database Table Sizes",
      "type": "table"
    }
  ],
  "refresh": "30s",
  "schemaVersion": 37,
  "style": "dark",
  "tags": ["metalayer", "airflow", "database"],
  "templating": {
    "list": []
  },
  "time": {
    "from": "now-1h",
    "to": "now"
  },
  "timepicker": {},
  "timezone": "",
  "title": "MetaLayer Airflow & Data Pipeline Dashboard",
  "uid": "metalayer-main",
  "version": 4
}