{
  "annotations": {
    "list": []
  },
  "description": "MetaLayer ETL Pipeline - Real Current Data Dashboard",
  "editable": true,
  "fiscalYearStartMonth": 0,
  "graphTooltip": 1,
  "id": null,
  "links": [],
  "liveNow": true,
  "panels": [
    {
      "datasource": {
        "type": "postgres",
        "uid": "PostgreSQL-ETL"
      },
      "fieldConfig": {
        "defaults": {
          "color": {
            "mode": "palette-classic"
          },
          "custom": {
            "hideFrom": {
              "legend": false,
              "tooltip": false,
              "vis": false
            }
          },
          "mappings": [],
          "unit": "short"
        },
        "overrides": []
      },
      "gridPos": {
        "h": 8,
        "w": 8,
        "x": 0,
        "y": 0
      },
      "id": 1,
      "options": {
        "legend": {
          "displayMode": "table",
          "placement": "bottom",
          "showLegend": true,
          "values": ["value"]
        },
        "pieType": "pie",
        "reduceOptions": {
          "calcs": [
            "lastNotNull"
          ],
          "fields": "",
          "values": false
        },
        "tooltip": {
          "mode": "single",
          "sort": "none"
        }
      },
      "targets": [
        {
          "datasource": {
            "type": "postgres",
            "uid": "PostgreSQL-ETL"
          },
          "editorMode": "code",
          "format": "table",
          "rawQuery": true,
          "rawSql": "SELECT \n  CASE \n    WHEN schemaname = 'bronze' THEN 'Bronze Layer'\n    WHEN schemaname = 'silver' THEN 'Silver Layer'\n    WHEN schemaname = 'gold' THEN 'Gold Layer'\n  END as layer,\n  SUM(n_live_tup) as record_count\nFROM pg_stat_user_tables \nWHERE schemaname IN ('bronze', 'silver', 'gold')\nGROUP BY schemaname\nORDER BY \n  CASE schemaname \n    WHEN 'bronze' THEN 1\n    WHEN 'silver' THEN 2\n    WHEN 'gold' THEN 3\n  END;",
          "refId": "A",
          "sql": {
            "columns": [
              {
                "parameters": [],
                "type": "function"
              }
            ],
            "groupBy": [
              {
                "property": {
                  "type": "string"
                },
                "type": "groupBy"
              }
            ],
            "limit": 50
          }
        }
      ],
      "title": "📊 Data Distribution by ETL Layer",
      "type": "piechart"
    },
    {
      "datasource": {
        "type": "postgres",
        "uid": "PostgreSQL-ETL"
      },
      "fieldConfig": {
        "defaults": {
          "color": {
            "mode": "thresholds"
          },
          "mappings": [],
          "thresholds": {
            "mode": "absolute",
            "steps": [
              {
                "color": "red",
                "value": null
              },
              {
                "color": "yellow",
                "value": 1000
              },
              {
                "color": "green",
                "value": 5000
              }
            ]
          },
          "unit": "short"
        },
        "overrides": [
          {
            "matcher": {
              "id": "byName",
              "options": "Bronze Records"
            },
            "properties": [
              {
                "id": "color",
                "value": {
                  "mode": "fixed",
                  "fixedColor": "#CD7F32"
                }
              }
            ]
          },
          {
            "matcher": {
              "id": "byName",
              "options": "Silver Records"
            },
            "properties": [
              {
                "id": "color",
                "value": {
                  "mode": "fixed",
                  "fixedColor": "#C0C0C0"
                }
              }
            ]
          },
          {
            "matcher": {
              "id": "byName",
              "options": "Gold Records"
            },
            "properties": [
              {
                "id": "color",
                "value": {
                  "mode": "fixed",
                  "fixedColor": "#FFD700"
                }
              }
            ]
          }
        ]
      },
      "gridPos": {
        "h": 8,
        "w": 8,
        "x": 8,
        "y": 0
      },
      "id": 2,
      "options": {
        "colorMode": "background",
        "graphMode": "area",
        "justifyMode": "center",
        "orientation": "horizontal",
        "reduceOptions": {
          "calcs": [
            "lastNotNull"
          ],
          "fields": "",
          "values": false
        },
        "textMode": "value_and_name"
      },
      "pluginVersion": "9.5.2",
      "targets": [
        {
          "datasource": {
            "type": "postgres",
            "uid": "PostgreSQL-ETL"
          },
          "editorMode": "code",
          "format": "table",
          "rawQuery": true,
          "rawSql": "SELECT \n  (SELECT SUM(n_live_tup) FROM pg_stat_user_tables WHERE schemaname = 'bronze') as \"Bronze Records\",\n  (SELECT SUM(n_live_tup) FROM pg_stat_user_tables WHERE schemaname = 'silver') as \"Silver Records\",\n  (SELECT SUM(n_live_tup) FROM pg_stat_user_tables WHERE schemaname = 'gold') as \"Gold Records\";",
          "refId": "A",
          "sql": {
            "columns": [
              {
                "parameters": [],
                "type": "function"
              }
            ],
            "groupBy": [
              {
                "property": {
                  "type": "string"
                },
                "type": "groupBy"
              }
            ],
            "limit": 50
          }
        }
      ],
      "title": "🥉🥈🥇 ETL Layer Status",
      "type": "stat"
    },
    {
      "datasource": {
        "type": "prometheus",
        "uid": "Prometheus"
      },
      "fieldConfig": {
        "defaults": {
          "color": {
            "mode": "thresholds"
          },
          "mappings": [
            {
              "options": {
                "0": {
                  "color": "red",
                  "index": 1,
                  "text": "DOWN ❌"
                },
                "1": {
                  "color": "green",
                  "index": 0,
                  "text": "UP ✅"
                }
              },
              "type": "value"
            }
          ],
          "thresholds": {
            "mode": "absolute",
            "steps": [
              {
                "color": "red",
                "value": null
              },
              {
                "color": "green",
                "value": 1
              }
            ]
          }
        },
        "overrides": []
      },
      "gridPos": {
        "h": 8,
        "w": 8,
        "x": 16,
        "y": 0
      },
      "id": 3,
      "options": {
        "colorMode": "background",
        "graphMode": "none",
        "justifyMode": "center",
        "orientation": "horizontal",
        "reduceOptions": {
          "calcs": [
            "lastNotNull"
          ],
          "fields": "",
          "values": false
        },
        "textMode": "auto"
      },
      "pluginVersion": "9.5.2",
      "targets": [
        {
          "datasource": {
            "type": "prometheus",
            "uid": "Prometheus"
          },
          "editorMode": "code",
          "expr": "up{job=~\"postgres|redis|node|prometheus\"}",
          "instant": false,
          "legendFormat": "{{job}}",
          "range": true,
          "refId": "A"
        }
      ],
      "title": "🚀 Infrastructure Services Status",
      "type": "stat"
    },
    {
      "datasource": {
        "type": "postgres",
        "uid": "PostgreSQL-ETL"
      },
      "fieldConfig": {
        "defaults": {
          "color": {
            "mode": "palette-classic"
          },
          "custom": {
            "axisLabel": "",
            "axisPlacement": "auto",
            "barAlignment": 0,
            "drawStyle": "line",
            "fillOpacity": 10,
            "gradientMode": "none",
            "hideFrom": {
              "legend": false,
              "tooltip": false,
              "vis": false
            },
            "lineInterpolation": "linear",
            "lineWidth": 2,
            "pointSize": 5,
            "scaleDistribution": {
              "type": "linear"
            },
            "showPoints": "auto",
            "spanNulls": false,
            "stacking": {
              "group": "A",
              "mode": "none"
            },
            "thresholdsStyle": {
              "mode": "off"
            }
          },
          "mappings": [],
          "thresholds": {
            "mode": "absolute",
            "steps": [
              {
                "color": "green",
                "value": null
              }
            ]
          },
          "unit": "currencyUSD"
        },
        "overrides": []
      },
      "gridPos": {
        "h": 8,
        "w": 12,
        "x": 0,
        "y": 8
      },
      "id": 4,
      "options": {
        "legend": {
          "calcs": [],
          "displayMode": "table",
          "placement": "right",
          "showLegend": true
        },
        "tooltip": {
          "mode": "single",
          "sort": "none"
        }
      },
      "targets": [
        {
          "datasource": {
            "type": "postgres",
            "uid": "PostgreSQL-ETL"
          },
          "editorMode": "code",
          "format": "table",
          "rawQuery": true,
          "rawSql": "SELECT \n  region,\n  total_revenue\nFROM gold.customer_analytics \nORDER BY total_revenue DESC\nLIMIT 10;",
          "refId": "A",
          "sql": {
            "columns": [
              {
                "parameters": [],
                "type": "function"
              }
            ],
            "groupBy": [
              {
                "property": {
                  "type": "string"
                },
                "type": "groupBy"
              }
            ],
            "limit": 50
          }
        }
      ],
      "title": "💰 Revenue by Region (Current Analytics)",
      "type": "barchart"
    },
    {
      "datasource": {
        "type": "postgres",
        "uid": "PostgreSQL-ETL"
      },
      "fieldConfig": {
        "defaults": {
          "color": {
            "mode": "palette-classic"
          },
          "custom": {
            "axisLabel": "",
            "axisPlacement": "auto",
            "barAlignment": 0,
            "drawStyle": "line",
            "fillOpacity": 10,
            "gradientMode": "none",
            "hideFrom": {
              "legend": false,
              "tooltip": false,
              "vis": false
            },
            "lineInterpolation": "linear",
            "lineWidth": 2,
            "pointSize": 5,
            "scaleDistribution": {
              "type": "linear"
            },
            "showPoints": "auto",
            "spanNulls": false,
            "stacking": {
              "group": "A",
              "mode": "none"
            },
            "thresholdsStyle": {
              "mode": "off"
            }
          },
          "mappings": [],
          "thresholds": {
            "mode": "absolute",
            "steps": [
              {
                "color": "green",
                "value": null
              }
            ]
          },
          "unit": "short"
        },
        "overrides": []
      },
      "gridPos": {
        "h": 8,
        "w": 12,
        "x": 12,
        "y": 8
      },
      "id": 5,
      "options": {
        "legend": {
          "calcs": [],
          "displayMode": "table",
          "placement": "right",
          "showLegend": true
        },
        "tooltip": {
          "mode": "single",
          "sort": "none"
        }
      },
      "targets": [
        {
          "datasource": {
            "type": "postgres",
            "uid": "PostgreSQL-ETL"
          },
          "editorMode": "code",
          "format": "table",
          "rawQuery": true,
          "rawSql": "SELECT \n  region,\n  total_customers\nFROM gold.customer_analytics \nORDER BY total_customers DESC\nLIMIT 10;",
          "refId": "A",
          "sql": {
            "columns": [
              {
                "parameters": [],
                "type": "function"
              }
            ],
            "groupBy": [
              {
                "property": {
                  "type": "string"
                },
                "type": "groupBy"
              }
            ],
            "limit": 50
          }
        }
      ],
      "title": "👥 Customers by Region (Current Analytics)",
      "type": "barchart"
    },
    {
      "datasource": {
        "type": "postgres",
        "uid": "PostgreSQL-ETL"
      },
      "fieldConfig": {
        "defaults": {
          "color": {
            "mode": "thresholds"
          },
          "custom": {
            "align": "auto",
            "cellOptions": {
              "type": "auto"
            },
            "inspect": false
          },
          "mappings": [],
          "thresholds": {
            "mode": "absolute",
            "steps": [
              {
                "color": "green",
                "value": null
              }
            ]
          }
        },
        "overrides": [
          {
            "matcher": {
              "id": "byName",
              "options": "total_revenue"
            },
            "properties": [
              {
                "id": "unit",
                "value": "currencyUSD"
              }
            ]
          },
          {
            "matcher": {
              "id": "byName",
              "options": "total_quantity_sold"
            },
            "properties": [
              {
                "id": "unit",
                "value": "short"
              }
            ]
          }
        ]
      },
      "gridPos": {
        "h": 8,
        "w": 24,
        "x": 0,
        "y": 16
      },
      "id": 6,
      "options": {
        "cellHeight": "sm",
        "footer": {
          "countRows": false,
          "fields": "",
          "reducer": [
            "sum"
          ],
          "show": false
        },
        "showHeader": true,
        "sortBy": [
          {
            "desc": true,
            "displayName": "total_revenue"
          }
        ]
      },
      "pluginVersion": "9.5.2",
      "targets": [
        {
          "datasource": {
            "type": "postgres",
            "uid": "PostgreSQL-ETL"
          },
          "editorMode": "code",
          "format": "table",
          "rawQuery": true,
          "rawSql": "SELECT \n  product_id,\n  total_orders,\n  total_quantity_sold,\n  total_revenue,\n  avg_order_value,\n  unique_customers\nFROM gold.product_analytics \nORDER BY total_revenue DESC\nLIMIT 20;",
          "refId": "A",
          "sql": {
            "columns": [
              {
                "parameters": [],
                "type": "function"
              }
            ],
            "groupBy": [
              {
                "property": {
                  "type": "string"
                },
                "type": "groupBy"
              }
            ],
            "limit": 50
          }
        }
      ],
      "title": "📦 Top Products Performance (Current Analytics)",
      "type": "table"
    },
    {
      "datasource": {
        "type": "postgres",
        "uid": "PostgreSQL-ETL"
      },
      "fieldConfig": {
        "defaults": {
          "color": {
            "mode": "thresholds"
          },
          "mappings": [],
          "thresholds": {
            "mode": "absolute",
            "steps": [
              {
                "color": "green",
                "value": null
              }
            ]
          },
          "unit": "bytes"
        },
        "overrides": []
      },
      "gridPos": {
        "h": 6,
        "w": 12,
        "x": 0,
        "y": 24
      },
      "id": 7,
      "options": {
        "colorMode": "value",
        "graphMode": "area",
        "justifyMode": "center",
        "orientation": "horizontal",
        "reduceOptions": {
          "calcs": [
            "lastNotNull"
          ],
          "fields": "",
          "values": false
        },
        "textMode": "auto"
      },
      "pluginVersion": "9.5.2",
      "targets": [
        {
          "datasource": {
            "type": "postgres",
            "uid": "PostgreSQL-ETL"
          },
          "editorMode": "code",
          "format": "table",
          "rawQuery": true,
          "rawSql": "SELECT \n  schemaname || '.' || relname as table_name,\n  pg_total_relation_size(schemaname||'.'||relname) as size_bytes\nFROM pg_stat_user_tables \nWHERE schemaname IN ('bronze', 'silver', 'gold')\nORDER BY size_bytes DESC;",
          "refId": "A",
          "sql": {
            "columns": [
              {
                "parameters": [],
                "type": "function"
              }
            ],
            "groupBy": [
              {
                "property": {
                  "type": "string"
                },
                "type": "groupBy"
              }
            ],
            "limit": 50
          }
        }
      ],
      "title": "💾 Storage Usage by Table",
      "type": "stat"
    },
    {
      "datasource": {
        "type": "postgres",
        "uid": "PostgreSQL-ETL"
      },
      "fieldConfig": {
        "defaults": {
          "color": {
            "mode": "thresholds"
          },
          "mappings": [],
          "thresholds": {
            "mode": "absolute",
            "steps": [
              {
                "color": "green",
                "value": null
              }
            ]
          },
          "unit": "dateTimeFromNow"
        },
        "overrides": []
      },
      "gridPos": {
        "h": 6,
        "w": 12,
        "x": 12,
        "y": 24
      },
      "id": 8,
      "options": {
        "colorMode": "background",
        "graphMode": "none",
        "justifyMode": "center",
        "orientation": "horizontal",
        "reduceOptions": {
          "calcs": [
            "lastNotNull"
          ],
          "fields": "",
          "values": false
        },
        "textMode": "auto"
      },
      "pluginVersion": "9.5.2",
      "targets": [
        {
          "datasource": {
            "type": "postgres",
            "uid": "PostgreSQL-ETL"
          },
          "editorMode": "code",
          "format": "table",
          "rawQuery": true,
          "rawSql": "SELECT \n  'Last Analytics Update' as metric,\n  EXTRACT(EPOCH FROM MAX(analytics_timestamp))::bigint * 1000 as timestamp_ms\nFROM gold.customer_analytics\nWHERE analytics_timestamp IS NOT NULL;",
          "refId": "A",
          "sql": {
            "columns": [
              {
                "parameters": [],
                "type": "function"
              }
            ],
            "groupBy": [
              {
                "property": {
                  "type": "string"
                },
                "type": "groupBy"
              }
            ],
            "limit": 50
          }
        }
      ],
      "title": "⏰ Last Data Refresh",
      "type": "stat"
    }
  ],
  "refresh": "30s",
  "schemaVersion": 38,
  "style": "dark",
  "tags": [
    "metalayer",
    "etl",
    "current-data",
    "production"
  ],
  "templating": {
    "list": []
  },
  "time": {
    "from": "now-1h",
    "to": "now"
  },
  "timepicker": {},
  "timezone": "",
  "title": "🚀 MetaLayer ETL - Current Data Dashboard",
  "uid": "metalayer-current-data",
  "version": 1,
  "weekStart": ""
}